resourceez/__init__.py
resourceez/api_object.py
resourceez-0.1.0.dist-info/LICENSE
resourceez-0.1.0.dist-info/WHEEL
resourceez-0.1.0.dist-info/METADATA
resourceez-0.1.0.dist-info/RECORD
