Metadata-Version: 2.1
Name: resourceez
Version: 0.1.0
Summary: A slim package for declaratively expressing, serialising and deserialising REST resources.
Author: tjweldon
Author-email: tomd90@gmail.com
Requires-Python: >=3.8,<4.0
Classifier: Programming Language :: Python :: 3
Classifier: Programming Language :: Python :: 3.10
Classifier: Programming Language :: Python :: 3.8
Classifier: Programming Language :: Python :: 3.9
Requires-Dist: requests (>=2.27.1,<3.0.0)
